CONTRIBUTING.md
LICENSE
MANIFEST.in
README.md
settings.ini
setup.py
calorie_count/__init__.py
calorie_count/_nbdev.py
calorie_count/core.py
calorie_count.egg-info/PKG-INFO
calorie_count.egg-info/SOURCES.txt
calorie_count.egg-info/dependency_links.txt
calorie_count.egg-info/not-zip-safe
calorie_count.egg-info/requires.txt
calorie_count.egg-info/top_level.txt
test/test.py