Metadata-Version: 2.1
Name: calorie-count
Version: 0.0.2
Summary: Project for SOF2 LAB
Home-page: https://github.com/hexann666/calorie_count/tree/branch/
Author: Anna Fedorova
Author-email: ms.afedorova@gmail.com
License: Apache Software License 2.0
Keywords: some keywords
Platform: UNKNOWN
Classifier: Development Status :: 3 - Alpha
Classifier: Intended Audience :: Developers
Classifier: Natural Language :: English
Classifier: Programming Language :: Python :: 3.6
Classifier: Programming Language :: Python :: 3.7
Classifier: Programming Language :: Python :: 3.8
Classifier: Programming Language :: Python :: 3.9
Classifier: Programming Language :: Python :: 3.10
Classifier: License :: OSI Approved :: Apache Software License
Requires-Python: >=3.6
Provides-Extra: dev
License-File: LICENSE
